Lab2/Problem2/traffic_light.v
module traffic_light(
    input  wire clk,
    input  wire rst,   // synchronous active-high reset
    input  wire tick,  // 1-cycle per-second pulse (1 Hz)
    output reg  ns_g, ns_y, ns_r,
    output reg  ew_g, ew_y, ew_r
);

    // State encoding (4 phases)
    localparam NS_GREEN  = 2'b00;
    localparam NS_YELLOW = 2'b01;
    localparam EW_GREEN  = 2'b10;
    localparam EW_YELLOW = 2'b11;

    reg [1:0] state, next_state;
    reg [2:0] tick_count;  // enough for up to 5–7 ticks

    // State register with sync reset
    always @(posedge clk) begin
        if (rst) begin
            state <= NS_GREEN;
            tick_count <= 3'd0;
        end else begin
            if (tick) begin
                if ((state == NS_GREEN  && tick_count == 3'd4) || // 5 ticks
                    (state == NS_YELLOW && tick_count == 3'd1) || // 2 ticks
                    (state == EW_GREEN  && tick_count == 3'd4) ||
                    (state == EW_YELLOW && tick_count == 3'd1)) begin
                        state <= next_state;
                        tick_count <= 3'd0;
                end else begin
                        tick_count <= tick_count + 1;
                end
            end
        end
    end

    // Next-state logic
    always @(*) begin
        case (state)
            NS_GREEN:  next_state = NS_YELLOW;
            NS_YELLOW: next_state = EW_GREEN;
            EW_GREEN:  next_state = EW_YELLOW;
            EW_YELLOW: next_state = NS_GREEN;
            default:   next_state = NS_GREEN;
        endcase
    end

    // Output logic (Moore: depends only on state)
    always @(*) begin
        // default all red
        ns_g=0; ns_y=0; ns_r=0;
        ew_g=0; ew_y=0; ew_r=0;
        case (state)
            NS_GREEN:  begin ns_g=1; ew_r=1; end
            NS_YELLOW: begin ns_y=1; ew_r=1; end
            EW_GREEN:  begin ew_g=1; ns_r=1; end
            EW_YELLOW: begin ew_y=1; ns_r=1; end
        endcase
    end

endmodule

Lab2/Problem2/tb_traffic_light.v
`timescale 1ns/1ps
module tb_traffic_light;

    reg clk, rst, tick;
    wire ns_g, ns_y, ns_r;
    wire ew_g, ew_y, ew_r;

    // DUT instantiation
    traffic_light dut(
        .clk(clk), .rst(rst), .tick(tick),
        .ns_g(ns_g), .ns_y(ns_y), .ns_r(ns_r),
        .ew_g(ew_g), .ew_y(ew_y), .ew_r(ew_r)
    );

    // 50MHz clock for example (20 ns period)
    always #10 clk = ~clk;

    initial begin
        // waveform dump
        $dumpfile("traffic.vcd");
        $dumpvars(0, tb_traffic_light);

        // init
        clk = 0;
        rst = 1;
        tick = 0;
        #25 rst = 0; // deassert reset

        // Generate tick pulses every 100ns (for simulation speed)
        repeat (40) begin
            #90 tick = 1;
            #20 tick = 0;
        end

        #100 $finish;
    end

    // Monitor outputs
    initial begin
        $monitor("T=%0t ns_g=%b ns_y=%b ns_r=%b | ew_g=%b ew_y=%b ew_r=%b | state=%b",
                  $time, ns_g, ns_y, ns_r, ew_g, ew_y, ew_r, dut.state);
    end

endmodule

Lab2/Problem2/traffic.vcd
$date
	Tue Aug 19 14:26:29 2025
$end
$version
	Icarus Verilog
$end
$timescale
	1ps
$end
$scope module tb_traffic_light $end
$var wire 1 ! ns_y $end
$var wire 1 " ns_r $end
$var wire 1 # ns_g $end
$var wire 1 $ ew_y $end
$var wire 1 % ew_r $end
$var wire 1 & ew_g $end
$var reg 1 ' clk $end
$var reg 1 ( rst $end
$var reg 1 ) tick $end
$scope module dut $end
$var wire 1 ' clk $end
$var wire 1 ( rst $end
$var wire 1 ) tick $end
$var parameter 2 * EW_GREEN $end
$var parameter 2 + EW_YELLOW $end
$var parameter 2 , NS_GREEN $end
$var parameter 2 - NS_YELLOW $end
$var reg 1 & ew_g $end
$var reg 1 % ew_r $end
$var reg 1 $ ew_y $end
$var reg 2 . next_state [1:0] $end
$var reg 1 # ns_g $end
$var reg 1 " ns_r $end
$var reg 1 ! ns_y $end
$var reg 2 / state [1:0] $end
$var reg 3 0 tick_count [2:0] $end
$upscope $end
$upscope $end
$enddefinitions $end
$comment Show the parameter values. $end
$dumpall
b1 -
b0 ,
b11 +
b10 *
$end
#0
$dumpvars
bx 0
bx /
bx .
0)
1(
0'
x&
x%
x$
x#
x"
x!
$end
#10000
1%
0$
0&
0"
0!
1#
b1 .
b0 0
b0 /
1'
#20000
0'
#25000
0(
#30000
1'
#40000
0'
#50000
1'
#60000
0'
#70000
1'
#80000
0'
#90000
1'
#100000
0'
#110000
1'
#115000
1)
#120000
0'
#130000
b1 0
1'
#135000
0)
#140000
0'
#150000
1'
#160000
0'
#170000
1'
#180000
0'
#190000
1'
#200000
0'
#210000
1'
#220000
0'
#225000
1)
#230000
b10 0
1'
#240000
0'
#245000
0)
#250000
1'
#260000
0'
#270000
1'
#280000
0'
#290000
1'
#300000
0'
#310000
1'
#320000
0'
#330000
1'
#335000
1)
#340000
0'
#350000
b11 0
1'
#355000
0)
#360000
0'
#370000
1'
#380000
0'
#390000
1'
#400000
0'
#410000
1'
#420000
0'
#430000
1'
#440000
0'
#445000
1)
#450000
b100 0
1'
#460000
0'
#465000
0)
#470000
1'
#480000
0'
#490000
1'
#500000
0'
#510000
1'
#520000
0'
#530000
1'
#540000
0'
#550000
1'
#555000
1)
#560000
0'
#570000
b10 .
1!
1%
0#
b0 0
b1 /
1'
#575000
0)
#580000
0'
#590000
1'
#600000
0'
#610000
1'
#620000
0'
#630000
1'
#640000
0'
#650000
1'
#660000
0'
#665000
1)
#670000
b1 0
1'
#680000
0'
#685000
0)
#690000
1'
#700000
0'
#710000
1'
#720000
0'
#730000
1'
#740000
0'
#750000
1'
#760000
0'
#770000
1'
#775000
1)
#780000
0'
#790000
1"
1&
0%
0!
b11 .
b0 0
b10 /
1'
#795000
0)
#800000
0'
#810000
1'
#820000
0'
#830000
1'
#840000
0'
#850000
1'
#860000
0'
#870000
1'
#880000
0'
#885000
1)
#890000
b1 0
1'
#900000
0'
#905000
0)
#910000
1'
#920000
0'
#930000
1'
#940000
0'
#950000
1'
#960000
0'
#970000
1'
#980000
0'
#990000
1'
#995000
1)
#1000000
0'
#1010000
b10 0
1'
#1015000
0)
#1020000
0'
#1030000
1'
#1040000
0'
#1050000
1'
#1060000
0'
#1070000
1'
#1080000
0'
#1090000
1'
#1100000
0'
#1105000
1)
#1110000
b11 0
1'
#1120000
0'
#1125000
0)
#1130000
1'
#1140000
0'
#1150000
1'
#1160000
0'
#1170000
1'
#1180000
0'
#1190000
1'
#1200000
0'
#1210000
1'
#1215000
1)
#1220000
0'
#1230000
b100 0
1'
#1235000
0)
#1240000
0'
#1250000
1'
#1260000
0'
#1270000
1'
#1280000
0'
#1290000
1'
#1300000
0'
#1310000
1'
#1320000
0'
#1325000
1)
#1330000
b0 .
1$
0&
1"
b0 0
b11 /
1'
#1340000
0'
#1345000
0)
#1350000
1'
#1360000
0'
#1370000
1'
#1380000
0'
#1390000
1'
#1400000
0'
#1410000
1'
#1420000
0'
#1430000
1'
#1435000
1)
#1440000
0'
#1450000
b1 0
1'
#1455000
0)
#1460000
0'
#1470000
1'
#1480000
0'
#1490000
1'
#1500000
0'
#1510000
1'
#1520000
0'
#1530000
1'
#1540000
0'
#1545000
1)
#1550000
1%
1#
0$
0"
b1 .
b0 0
b0 /
1'
#1560000
0'
#1565000
0)
#1570000
1'
#1580000
0'
#1590000
1'
#1600000
0'
#1610000
1'
#1620000
0'
#1630000
1'
#1640000
0'
#1650000
1'
#1655000
1)
#1660000
0'
#1670000
b1 0
1'
#1675000
0)
#1680000
0'
#1690000
1'
#1700000
0'
#1710000
1'
#1720000
0'
#1730000
1'
#1740000
0'
#1750000
1'
#1760000
0'
#1765000
1)
#1770000
b10 0
1'
#1780000
0'
#1785000
0)
#1790000
1'
#1800000
0'
#1810000
1'
#1820000
0'
#1830000
1'
#1840000
0'
#1850000
1'
#1860000
0'
#1870000
1'
#1875000
1)
#1880000
0'
#1890000
b11 0
1'
#1895000
0)
#1900000
0'
#1910000
1'
#1920000
0'
#1930000
1'
#1940000
0'
#1950000
1'
#1960000
0'
#1970000
1'
#1980000
0'
#1985000
1)
#1990000
b100 0
1'
#2000000
0'
#2005000
0)
#2010000
1'
#2020000
0'
#2030000
1'
#2040000
0'
#2050000
1'
#2060000
0'
#2070000
1'
#2080000
0'
#2090000
1'
#2095000
1)
#2100000
0'
#2110000
b10 .
1!
1%
0#
b0 0
b1 /
1'
#2115000
0)
#2120000
0'
#2130000
1'
#2140000
0'
#2150000
1'
#2160000
0'
#2170000
1'
#2180000
0'
#2190000
1'
#2200000
0'
#2205000
1)
#2210000
b1 0
1'
#2220000
0'
#2225000
0)
#2230000
1'
#2240000
0'
#2250000
1'
#2260000
0'
#2270000
1'
#2280000
0'
#2290000
1'
#2300000
0'
#2310000
1'
#2315000
1)
#2320000
0'
#2330000
1"
1&
0%
0!
b11 .
b0 0
b10 /
1'
#2335000
0)
#2340000
0'
#2350000
1'
#2360000
0'
#2370000
1'
#2380000
0'
#2390000
1'
#2400000
0'
#2410000
1'
#2420000
0'
#2425000
1)
#2430000
b1 0
1'
#2440000
0'
#2445000
0)
#2450000
1'
#2460000
0'
#2470000
1'
#2480000
0'
#2490000
1'
#2500000
0'
#2510000
1'
#2520000
0'
#2530000
1'
#2535000
1)
#2540000
0'
#2550000
b10 0
1'
#2555000
0)
#2560000
0'
#2570000
1'
#2580000
0'
#2590000
1'
#2600000
0'
#2610000
1'
#2620000
0'
#2630000
1'
#2640000
0'
#2645000
1)
#2650000
b11 0
1'
#2660000
0'
#2665000
0)
#2670000
1'
#2680000
0'
#2690000
1'
#2700000
0'
#2710000
1'
#2720000
0'
#2730000
1'
#2740000
0'
#2750000
1'
#2755000
1)
#2760000
0'
#2770000
b100 0
1'
#2775000
0)
#2780000
0'
#2790000
1'
#2800000
0'
#2810000
1'
#2820000
0'
#2830000
1'
#2840000
0'
#2850000
1'
#2860000
0'
#2865000
1)
#2870000
b0 .
1$
0&
1"
b0 0
b11 /
1'
#2880000
0'
#2885000
0)
#2890000
1'
#2900000
0'
#2910000
1'
#2920000
0'
#2930000
1'
#2940000
0'
#2950000
1'
#2960000
0'
#2970000
1'
#2975000
1)
#2980000
0'
#2990000
b1 0
1'
#2995000
0)
#3000000
0'
#3010000
1'
#3020000
0'
#3030000
1'
#3040000
0'
#3050000
1'
#3060000
0'
#3070000
1'
#3080000
0'
#3085000
1)
#3090000
1%
1#
0$
0"
b1 .
b0 0
b0 /
1'
#3100000
0'
#3105000
0)
#3110000
1'
#3120000
0'
#3130000
1'
#3140000
0'
#3150000
1'
#3160000
0'
#3170000
1'
#3180000
0'
#3190000
1'
#3195000
1)
#3200000
0'
#3210000
b1 0
1'
#3215000
0)
#3220000
0'
#3230000
1'
#3240000
0'
#3250000
1'
#3260000
0'
#3270000
1'
#3280000
0'
#3290000
1'
#3300000
0'
#3305000
1)
#3310000
b10 0
1'
#3320000
0'
#3325000
0)
#3330000
1'
#3340000
0'
#3350000
1'
#3360000
0'
#3370000
1'
#3380000
0'
#3390000
1'
#3400000
0'
#3410000
1'
#3415000
1)
#3420000
0'
#3430000
b11 0
1'
#3435000
0)
#3440000
0'
#3450000
1'
#3460000
0'
#3470000
1'
#3480000
0'
#3490000
1'
#3500000
0'
#3510000
1'
#3520000
0'
#3525000
1)
#3530000
b100 0
1'
#3540000
0'
#3545000
0)
#3550000
1'
#3560000
0'
#3570000
1'
#3580000
0'
#3590000
1'
#3600000
0'
#3610000
1'
#3620000
0'
#3630000
1'
#3635000
1)
#3640000
0'
#3650000
b10 .
1!
1%
0#
b0 0
b1 /
1'
#3655000
0)
#3660000
0'
#3670000
1'
#3680000
0'
#3690000
1'
#3700000
0'
#3710000
1'
#3720000
0'
#3730000
1'
#3740000
0'
#3745000
1)
#3750000
b1 0
1'
#3760000
0'
#3765000
0)
#3770000
1'
#3780000
0'
#3790000
1'
#3800000
0'
#3810000
1'
#3820000
0'
#3830000
1'
#3840000
0'
#3850000
1'
#3855000
1)
#3860000
0'
#3870000
1"
1&
0%
0!
b11 .
b0 0
b10 /
1'
#3875000
0)
#3880000
0'
#3890000
1'
#3900000
0'
#3910000
1'
#3920000
0'
#3930000
1'
#3940000
0'
#3950000
1'
#3960000
0'
#3965000
1)
#3970000
b1 0
1'
#3980000
0'
#3985000
0)
#3990000
1'
#4000000
0'
#4010000
1'
#4020000
0'
#4030000
1'
#4040000
0'
#4050000
1'
#4060000
0'
#4070000
1'
#4075000
1)
#4080000
0'
#4090000
b10 0
1'
#4095000
0)
#4100000
0'
#4110000
1'
#4120000
0'
#4130000
1'
#4140000
0'
#4150000
1'
#4160000
0'
#4170000
1'
#4180000
0'
#4185000
1)
#4190000
b11 0
1'
#4200000
0'
#4205000
0)
#4210000
1'
#4220000
0'
#4230000
1'
#4240000
0'
#4250000
1'
#4260000
0'
#4270000
1'
#4280000
0'
#4290000
1'
#4295000
1)
#4300000
0'
#4310000
b100 0
1'
#4315000
0)
#4320000
0'
#4330000
1'
#4340000
0'
#4350000
1'
#4360000
0'
#4370000
1'
#4380000
0'
#4390000
1'
#4400000
0'
#4405000
1)
#4410000
b0 .
1$
0&
1"
b0 0
b11 /
1'
#4420000
0'
#4425000
0)
