Lab2/Problem3/vending_mealy.v
module vending_mealy(
    input  wire       clk,
    input  wire       rst,     
    input  wire [1:0] coin,    
    output reg        dispense, 
    output reg        chg5     
);

    
    parameter S0  = 2'b00,
              S5  = 2'b01,
              S10 = 2'b10,
              S15 = 2'b11;

    reg [1:0] state, next_state;

    
    always @(posedge clk) begin
        if (rst)
            state <= S0;
        else
            state <= next_state;
    end

  
    always @(*) begin
      
        next_state = state;
        dispense   = 1'b0;
        chg5       = 1'b0;

        case (state)
            S0: begin
                if (coin == 2'b01) next_state = S5;       
                else if (coin == 2'b10) next_state = S10; 
            end

            S5: begin
                if (coin == 2'b01) next_state = S10;
                else if (coin == 2'b10) next_state = S15;
            end

            S10: begin
                if (coin == 2'b01) next_state = S15;
                else if (coin == 2'b10) begin
                    dispense   = 1'b1; 
                    next_state = S0;  
                end
            end

            S15: begin
                if (coin == 2'b01) begin
                    dispense   = 1'b1;
                    next_state = S0;  
                end
                else if (coin == 2'b10) begin
                    dispense   = 1'b1; 
                    chg5       = 1'b1;
                    next_state = S0;
                end
            end
        endcase
    end
endmodule

Lab2/Problem3/tb_vending_mealy.v
`timescale 1ns/1ps
module tb_vending_mealy;
    reg clk, rst;
    reg [1:0] coin;
    wire dispense, chg5;

    vending_mealy dut(.clk(clk), .rst(rst), .coin(coin),
                      .dispense(dispense), .chg5(chg5));

    
    initial clk = 0;
    always #5 clk = ~clk;

   
    task put5;
        begin
            coin = 2'b01; #10;
            coin = 2'b00; #10;
        end
    endtask

    task put10;
        begin
            coin = 2'b10; #10;
            coin = 2'b00; #10;
        end
    endtask

   
    initial begin
        $dumpfile("vending.vcd");
        $dumpvars(0, tb_vending_mealy);

        
        coin = 2'b00;
        rst  = 1;
        #15 rst = 0;

       
        put10; put10;

       
        put5; put5; put10;

      
        put10; put10; put5;

        #100 $finish;
    end
endmodule

Lab2/Problem3/vending.vcd
$date
	Tue Aug 19 14:31:12 2025
$end
$version
	Icarus Verilog
$end
$timescale
	1ps
$end
$scope module tb_vending_mealy $end
$var wire 1 ! dispense $end
$var wire 1 " chg5 $end
$var reg 1 # clk $end
$var reg 2 $ coin [1:0] $end
$var reg 1 % rst $end
$scope module dut $end
$var wire 1 # clk $end
$var wire 2 & coin [1:0] $end
$var wire 1 % rst $end
$var parameter 2 ' S0 $end
$var parameter 2 ( S10 $end
$var parameter 2 ) S15 $end
$var parameter 2 * S5 $end
$var reg 1 " chg5 $end
$var reg 1 ! dispense $end
$var reg 2 + next_state [1:0] $end
$var reg 2 , state [1:0] $end
$upscope $end
$scope task put10 $end
$upscope $end
$scope task put5 $end
$upscope $end
$upscope $end
$enddefinitions $end
$comment Show the parameter values. $end
$dumpall
b1 *
b11 )
b10 (
b0 '
$end
#0
$dumpvars
bx ,
bx +
b0 &
1%
b0 $
0#
0"
0!
$end
#5000
b0 +
b0 ,
1#
#10000
0#
#15000
1!
b10 ,
b0 +
1#
b10 $
b10 &
0%
#20000
0#
#25000
0!
b10 +
1#
b0 $
b0 &
#30000
0#
#35000
b0 ,
b10 +
0!
1#
b10 $
b10 &
#40000
0#
#45000
b0 +
1#
b0 $
b0 &
#50000
0#
#55000
b1 ,
b10 +
1#
b1 $
b1 &
#60000
0#
#65000
b1 +
1#
b0 $
b0 &
#70000
0#
#75000
b10 ,
b11 +
1#
b1 $
b1 &
#80000
0#
#85000
b10 +
1#
b0 $
b0 &
#90000
0#
#95000
b0 ,
b10 +
0!
1#
b10 $
b10 &
#100000
0#
#105000
b0 +
1#
b0 $
b0 &
#110000
0#
#115000
1!
b10 ,
b0 +
1#
b10 $
b10 &
#120000
0#
#125000
0!
b10 +
1#
b0 $
b0 &
#130000
0#
#135000
b0 ,
b10 +
0!
1#
b10 $
b10 &
#140000
0#
#145000
b0 +
1#
b0 $
b0 &
#150000
0#
#155000
b1 ,
b10 +
1#
b1 $
b1 &
#160000
0#
#165000
b1 +
1#
b0 $
b0 &
