Lab2/Problem1/seq_detect_mealy.v
module seq_detect_mealy(
    input  wire clk,
    input  wire rst,   
    input  wire din,   
    output reg  y      
);

 
    localparam S0 = 2'b00; 
    localparam S1 = 2'b01; 
    localparam S2 = 2'b10; 
    localparam S3 = 2'b11; 

    reg [1:0] state, next_state;

    
    always @(posedge clk) begin
        if (rst)
            state <= S0;
        else
            state <= next_state;
    end

   
    always @(*) begin
        next_state = state;
        y = 1'b0;  
        case (state)
            S0: next_state = (din) ? S1 : S0;

            S1: next_state = (din) ? S2 : S0;

            S2: next_state = (din) ? S2 : S3;

            S3: begin
                if (din) begin
                    next_state = S1;
                    y = 1'b1; // detect 1101
                end else begin
                    next_state = S0;
                end
            end

            default: next_state = S0;
        endcase
    end

endmodule

Lab2/Problem1/tb_seq_detect_mealy.v
`timescale 1ns/1ps
module tb_seq_detect_mealy;
    reg clk, rst, din;
    wire y;

    // DUT instantiation
    seq_detect_mealy dut(
        .clk(clk),
        .rst(rst),
        .din(din),
        .y(y)
    );

    // Clock gen: 100 MHz (10ns period)
    always #5 clk = ~clk;

    initial begin
        // Dumpfile for GTKWave
        $dumpfile("dump.vcd");
        $dumpvars(0, tb_seq_detect_mealy);

        // Initialize
        clk = 0;
        rst = 1;
        din = 0;
        #12 rst = 0; // deassert reset after few cycles

        // Bitstream with overlaps: 11011011101
        send_bits(11'b11011011101);

        #50 $finish;
    end

    // Task to send bits MSB-first
    task send_bits(input [31:0] data);
        integer i;
        begin
            for (i=$bits(data)-1; i>=0; i=i-1) begin
                din = data[i];
                #10; // 1 clock cycle per bit
            end
        end
    endtask

    // Monitor
    initial begin
        $monitor("T=%0t din=%b y=%b state=%b",
                 $time, din, y, dut.state);
    end

endmodule

Lab2/Problem1/dump.vcd
$date
	Tue Aug 19 14:20:18 2025
$end
$version
	Icarus Verilog
$end
$timescale
	1ps
$end
$scope module tb_seq_detect_mealy $end
$var wire 1 ! y $end
$var reg 1 " clk $end
$var reg 1 # din $end
$var reg 1 $ rst $end
$scope module dut $end
$var wire 1 " clk $end
$var wire 1 # din $end
$var wire 1 $ rst $end
$var parameter 2 % S0 $end
$var parameter 2 & S1 $end
$var parameter 2 ' S2 $end
$var parameter 2 ( S3 $end
$var reg 2 ) next_state [1:0] $end
$var reg 2 * state [1:0] $end
$var reg 1 ! y $end
$upscope $end
$scope task send_bits $end
$var reg 32 + data [31:0] $end
$var integer 32 , i [31:0] $end
$upscope $end
$upscope $end
$enddefinitions $end
$comment Show the parameter values. $end
$dumpall
b11 (
b10 '
b1 &
b0 %
$end
#0
$dumpvars
bx ,
bx +
bx *
b0 )
1$
0#
0"
0!
$end
#5000
b0 *
1"
#10000
0"
#12000
b11111 ,
b11011011101 +
0$
#15000
1"
#20000
0"
#22000
b11110 ,
#25000
1"
#30000
0"
#32000
b11101 ,
#35000
1"
#40000
0"
#42000
b11100 ,
#45000
1"
#50000
0"
#52000
b11011 ,
#55000
1"
#60000
0"
#62000
b11010 ,
#65000
1"
#70000
0"
#72000
b11001 ,
#75000
1"
#80000
0"
#82000
b11000 ,
#85000
1"
#90000
0"
#92000
b10111 ,
#95000
1"
#100000
0"
#102000
b10110 ,
#105000
1"
#110000
0"
#112000
b10101 ,
#115000
1"
#120000
0"
#122000
b10100 ,
#125000
1"
#130000
0"
#132000
b10011 ,
#135000
1"
#140000
0"
#142000
b10010 ,
#145000
1"
#150000
0"
#152000
b10001 ,
#155000
1"
#160000
0"
#162000
b10000 ,
#165000
1"
#170000
0"
#172000
b1111 ,
#175000
1"
#180000
0"
#182000
b1110 ,
#185000
1"
#190000
0"
#192000
b1101 ,
#195000
1"
#200000
0"
#202000
b1100 ,
#205000
1"
#210000
0"
#212000
b1011 ,
#215000
1"
#220000
0"
#222000
b1 )
1#
b1010 ,
#225000
b10 )
b1 *
1"
#230000
0"
#232000
b1001 ,
#235000
b10 *
1"
#240000
0"
#242000
b11 )
0#
b1000 ,
#245000
b0 )
b11 *
1"
#250000
0"
#252000
1!
b1 )
1#
b111 ,
#255000
b10 )
0!
b1 *
1"
#260000
0"
#262000
b110 ,
#265000
b10 *
1"
#270000
0"
#272000
b11 )
0#
b101 ,
#275000
b0 )
b11 *
1"
#280000
0"
#282000
1!
b1 )
1#
b100 ,
#285000
b10 )
0!
b1 *
1"
#290000
0"
#292000
b11 ,
#295000
b10 *
1"
#300000
0"
#302000
b10 ,
#305000
1"
#310000
0"
#312000
b11 )
0#
b1 ,
#315000
b0 )
b11 *
1"
#320000
0"
#322000
1!
b1 )
1#
b0 ,
#325000
b10 )
0!
b1 *
1"
#330000
0"
#332000
b11111111111111111111111111111111 ,
#335000
b10 *
1"
